ross_cli/__init__.py
ross_cli/cli.py
ross_cli/constants.py
ross_cli/commands/index.py
ross_cli/commands/init.py
ross_cli/commands/install.py
ross_cli/commands/release.py
ross_cli/commands/tap.py
ross_cli/git/github.py
ross_cli/git/index.py
ross_cli/utils/check_gh.py
ross_cli/utils/config.py
ross_cli/utils/linux_install.sh
ross_cli/utils/rossproject.py
ross_cli/utils/urls.py
ross_cli/utils/venv.py
ross_cli-0.3.8.dist-info/METADATA
ross_cli-0.3.8.dist-info/WHEEL
ross_cli-0.3.8.dist-info/entry_points.txt
ross_cli-0.3.8.dist-info/licenses/LICENSE
ross_cli-0.3.8.dist-info/RECORD
