Metadata-Version: 2.4
Name: ross-cli
Version: 0.3.8
Summary: CLI for data analysis code reuse in MATLAB, Python, and R.
Project-URL: Homepage, https://github.com/ResearchOS/ross_cli
Project-URL: Repository, https://github.com/ResearchOS/ross_cli
Project-URL: Documentation, https://ResearchOS.github.io/ross_cli/
Author-email: Mitchell Tillman <mtillman14@gmail.com>
Maintainer-email: Mitchell Tillman <mtillman14@gmail.com>
License-Expression: MIT
License-File: LICENSE
Classifier: Development Status :: 4 - Beta
Classifier: Intended Audience :: Science/Research
Classifier: License :: OSI Approved :: MIT License
Classifier: Operating System :: OS Independent
Classifier: Topic :: Software Development
Classifier: Topic :: System :: Software Distribution
Requires-Python: >=3.9
Requires-Dist: tomli
Requires-Dist: tomli-w
Requires-Dist: typer
